[
  {
    "id": 1,
    "name": "Giải Vô Địch Cầu Lông Quốc Gia 2024",
    "nameEn": "National Badminton Championship 2024",
    "startDate": "2024-12-15",
    "endDate": "2024-12-22",
    "location": "Nhà thi đấu Quân khu 7, TP.HCM",
    "locationEn": "Military Region 7 Stadium, HCMC",
    "status": "upcoming",
    "participants": 256,
    "prize": "500,000,000 VNĐ",
    "image": "/icons/tournaments/national-championship.svg",
    "category": "professional",
    "description": "Giải đấu cầu lông lớn nhất năm với sự tham gia của các VĐV hàng đầu cả nước",
    "registrationDeadline": "2024-12-01",
    "featured": true
  },
  {
    "id": 2,
    "name": "Cúp Mùa Xuân 2025",
    "nameEn": "Spring Cup 2025",
    "startDate": "2025-02-10",
    "endDate": "2025-02-14",
    "location": "Sân cầu lông Linh Đàm, Hà Nội",
    "locationEn": "Linh Dam Badminton Court, Hanoi",
    "status": "registration",
    "participants": 128,
    "prize": "200,000,000 VNĐ",
    "image": "/icons/tournaments/spring-cup.svg",
    "category": "amateur",
    "description": "Giải đấu chào mừng Tết Nguyên Đán, mở rộng cho tất cả các trình độ",
    "registrationDeadline": "2025-01-31",
    "featured": true
  },
  {
    "id": 3,
    "name": "Giải Câu Lạc Bộ Miền Nam",
    "nameEn": "Southern Club Tournament",
    "startDate": "2024-11-20",
    "endDate": "2024-11-24",
    "location": "Trung tâm Cầu Lông Rạch Miễu, Tiền Giang",
    "locationEn": "Rach Mieu Badminton Center, Tien Giang",
    "status": "ongoing",
    "participants": 96,
    "prize": "150,000,000 VNĐ",
    "image": "/icons/tournaments/southern-club.svg",
    "category": "club",
    "description": "Giải đấu giao lưu giữa các CLB cầu lông miền Nam",
    "registrationDeadline": "2024-11-10",
    "featured": false
  },
  {
    "id": 4,
    "name": "Giải U19 Toàn Quốc",
    "nameEn": "National U19 Championship",
    "startDate": "2025-01-05",
    "endDate": "2025-01-10",
    "location": "Cung Thể Thao Tiên Sơn, Đà Nẵng",
    "locationEn": "Tien Son Sports Palace, Da Nang",
    "status": "upcoming",
    "participants": 200,
    "prize": "100,000,000 VNĐ",
    "image": "/icons/tournaments/u19-championship.svg",
    "category": "youth",
    "description": "Giải đấu dành cho tài năng trẻ dưới 19 tuổi trên toàn quốc",
    "registrationDeadline": "2024-12-20",
    "featured": true
  },
  {
    "id": 5,
    "name": "Giải Cầu Lông Doanh Nghiệp",
    "nameEn": "Corporate Badminton League",
    "startDate": "2024-11-25",
    "endDate": "2024-11-30",
    "location": "Nhà thi đấu Phú Thọ, TP.HCM",
    "locationEn": "Phu Tho Stadium, HCMC",
    "status": "registration",
    "participants": 64,
    "prize": "80,000,000 VNĐ",
    "image": "/icons/tournaments/corporate-league.svg",
    "category": "corporate",
    "description": "Giải đấu dành cho nhân viên các công ty, doanh nghiệp",
    "registrationDeadline": "2024-11-18",
    "featured": false
  },
  {
    "id": 6,
    "name": "Giải Vô Địch Đôi Nam Nữ",
    "nameEn": "Mixed Doubles Championship",
    "startDate": "2024-12-08",
    "endDate": "2024-12-12",
    "location": "Sân Cầu Lông Chuyên Nghiệp VBA, Hà Nội",
    "locationEn": "VBA Professional Court, Hanoi",
    "status": "upcoming",
    "participants": 80,
    "prize": "120,000,000 VNĐ",
    "image": "/icons/tournaments/mixed-doubles.svg",
    "category": "professional",
    "description": "Giải đấu chuyên biệt dành cho nội dung đôi nam nữ",
    "registrationDeadline": "2024-11-28",
    "featured": true
  },
  {
    "id": 7,
    "name": "Giải Cựu Cầu Thủ Chuyên Nghiệp",
    "nameEn": "Veterans Professional Cup",
    "startDate": "2025-03-15",
    "endDate": "2025-03-18",
    "location": "Nhà thi đấu Nguyễn Du, Đà Nẵng",
    "locationEn": "Nguyen Du Stadium, Da Nang",
    "status": "upcoming",
    "participants": 48,
    "prize": "50,000,000 VNĐ",
    "image": "/icons/tournaments/veterans-cup.svg",
    "category": "veteran",
    "description": "Giải đấu dành cho các cựu vận động viên chuyên nghiệp trên 40 tuổi",
    "registrationDeadline": "2025-03-01",
    "featured": false
  },
  {
    "id": 8,
    "name": "Giải Mở Rộng TP.HCM",
    "nameEn": "HCMC Open Tournament",
    "startDate": "2024-11-15",
    "endDate": "2024-11-17",
    "location": "Cung Văn Hóa Lao Động, TP.HCM",
    "locationEn": "Labor Cultural Palace, HCMC",
    "status": "completed",
    "participants": 120,
    "prize": "100,000,000 VNĐ",
    "image": "/icons/tournaments/hcmc-open.svg",
    "category": "open",
    "description": "Giải đấu mở rộng thu hút nhiều VĐV trong và ngoài TP.HCM",
    "registrationDeadline": "2024-11-05",
    "featured": false,
    "winner": "Nguyễn Văn A - CLB Thành Phố",
    "runnerUp": "Trần Thị B - CLB Bình Thạnh"
  }
]
